quickmock
